COPYING
LICENSE
MANIFEST.in
README.rst
distribute_setup.py
setup.py
Orange_Text.egg-info/PKG-INFO
Orange_Text.egg-info/SOURCES.txt
Orange_Text.egg-info/dependency_links.txt
Orange_Text.egg-info/entry_points.txt
Orange_Text.egg-info/not-zip-safe
Orange_Text.egg-info/requires.txt
Orange_Text.egg-info/top_level.txt
_text/__init__.py
_text/orngText.py
_text/orngTextWrapper.py
_text/datasets/lem-bg.bin
_text/datasets/lem-cs.bin
_text/datasets/lem-en.bin
_text/datasets/lem-es.bin
_text/datasets/lem-et.bin
_text/datasets/lem-fr.bin
_text/datasets/lem-ge.bin
_text/datasets/lem-hr.fsa
_text/datasets/lem-hu.bin
_text/datasets/lem-it.bin
_text/datasets/lem-ro.bin
_text/datasets/lem-sl.bin
_text/datasets/lem-sr.bin
_text/datasets/stopwords_en.txt
_text/datasets/stopwords_fr.txt
_text/datasets/stopwords_hr.txt
_text/widgets/OWBagofWords.py
_text/widgets/OWLetterNgram.py
_text/widgets/OWTextDistance.py
_text/widgets/OWTextFeatureSelection.py
_text/widgets/OWTextFile.py
_text/widgets/OWTextPreprocess.py
_text/widgets/OWWordNgram.py
_text/widgets/__init__.py
_text/widgets/icons/BagOfWords.png
_text/widgets/icons/LetterNgram.png
_text/widgets/icons/TextDistance.png
_text/widgets/icons/TextFeatureSelection.png
_text/widgets/icons/TextFile.png
_text/widgets/icons/TextPreprocess.png
_text/widgets/icons/WordNgram.png
_text/widgets/icons/bg.png
_text/widgets/icons/cs.png
_text/widgets/icons/en.png
_text/widgets/icons/es.png
_text/widgets/icons/et.png
_text/widgets/icons/fr.png
_text/widgets/icons/ge.png
_text/widgets/icons/hr.png
_text/widgets/icons/hu.png
_text/widgets/icons/it.png
_text/widgets/icons/ro.png
_text/widgets/icons/sl.png
_text/widgets/icons/sr.png
_text/widgets/prototypes/OWCorrAnalysis.py
_text/widgets/prototypes/OWCorrAnalysisGraph.py
_text/widgets/prototypes/__init__.py
docs/Makefile
docs/rst/conf.py
docs/rst/index.rst
scripts/post_install_script.py
scripts/textConfiguration.py
src/Makefile
src/lemmagen/RdrLemmatizer.cpp
src/lemmagen/RdrLemmatizer.h
src/orngTextWrapper/Wrapper.cpp
src/orngTextWrapper/Wrapper.h
src/orngTextWrapper/Wrapper.i
src/orngTextWrapper/Wrapper_wrap.cxx
src/tmt/common/Common.cpp
src/tmt/common/Common.h
src/tmt/common/Files.cpp
src/tmt/common/Files.h
